LICENSE
MANIFEST.in
README.md
requirements.txt
setup.py
ofrak_patch_maker/__init__.py
ofrak_patch_maker/model.py
ofrak_patch_maker/patch_maker.py
ofrak_patch_maker/py.typed
ofrak_patch_maker/toolchain.conf
ofrak_patch_maker.egg-info/LICENSE
ofrak_patch_maker.egg-info/PKG-INFO
ofrak_patch_maker.egg-info/SOURCES.txt
ofrak_patch_maker.egg-info/dependency_links.txt
ofrak_patch_maker.egg-info/requires.txt
ofrak_patch_maker.egg-info/top_level.txt
ofrak_patch_maker/binary_parser/__init__.py
ofrak_patch_maker/binary_parser/abstract.py
ofrak_patch_maker/binary_parser/gnu.py
ofrak_patch_maker/binary_parser/llvm.py
ofrak_patch_maker/toolchain/__init__.py
ofrak_patch_maker/toolchain/abstract.py
ofrak_patch_maker/toolchain/gnu.py
ofrak_patch_maker/toolchain/gnu_aarch64.py
ofrak_patch_maker/toolchain/gnu_arm.py
ofrak_patch_maker/toolchain/gnu_avr.py
ofrak_patch_maker/toolchain/gnu_m68k.py
ofrak_patch_maker/toolchain/gnu_ppc.py
ofrak_patch_maker/toolchain/gnu_vbcc_m68k.py
ofrak_patch_maker/toolchain/gnu_x64.py
ofrak_patch_maker/toolchain/llvm_12.py
ofrak_patch_maker/toolchain/model.py
ofrak_patch_maker/toolchain/utils.py